reminder/VERSION.txt
reminder/__info__.py
reminder/__init__.py
reminder/__main__.py
reminder_detector-1.2.2.dist-info/LICENSE
reminder_detector-1.2.2.dist-info/METADATA
reminder_detector-1.2.2.dist-info/WHEEL
reminder_detector-1.2.2.dist-info/entry_points.txt
reminder_detector-1.2.2.dist-info/top_level.txt
reminder_detector-1.2.2.dist-info/RECORD
