Metadata-Version: 2.1
Name: reminder-detector
Version: 1.2.2
Summary: Implementation of the packing detection heuristic from the paper "Packed PE File Detection for Malware Forensics" of Han et al.
Author-email: Alexandre D'Hondt <alexandre.dhondt@gmail.com>
License:                     GNU GENERAL PUBLIC LICENSE
Project-URL: homepage, https://github.com/packing-box/reminder
Project-URL: issues, https://github.com/packing-box/reminder/issues
Project-URL: repository, https://github.com/packing-box/reminder
Keywords: packing,packed-executable,packing-detection
Classifier: Development Status :: 5 - Production/Stable
Classifier: Environment :: Console
Classifier: Intended Audience :: Developers
Classifier: Intended Audience :: Information Technology
Classifier: Intended Audience :: Other Audience
Classifier: License :: OSI Approved :: GNU General Public License v3 or later (GPLv3+)
Classifier: Programming Language :: Python :: 3
Classifier: Topic :: Software Development :: Libraries :: Python Modules
Classifier: Topic :: Security
Requires-Python: <4,>=3.8
License-File: LICENSE
Requires-Dist: lief>=0.15.1
